{
  "setup_id": "BTCUSDT-2026-04-04-001",
  "generated_at": "2026-04-04T08:00:00Z",
  "symbol": "BTCUSDT",
  "exchange": "binance",
  "market_type": "futures",
  "is_perpetual": true,
  "data_quality": {
    "is_complete": true,
    "has_null_values": false,
    "indicator_validity": true,
    "candle_consistency": true
  },
  "risk_config": {
    "account_size": 1000,
    "risk_percent": 1,
    "leverage": 5
  },
  "validation_rules": {
    "min_rr": 2.0,
    "rsi_zone_for_long": [50, 70],
    "rsi_zone_for_short": [30, 50],
    "max_distance_to_resistance_atr_multiple": 1.0,
    "min_sl_atr_multiple": 0.8,
    "min_tp1_atr_multiple": 1.5,
    "require_htf_trend_alignment": true
  },
  "timeframe_roles": {
    "4h": "macro_context",
    "1h": "bias",
    "15m": "setup",
    "1m": "trigger"
  },
  "current_context": {
    "price": 68290.3,
    "trend": "bullish",
    "session": "asia",
    "volatility_state": "normal"
  },
  "setup_candidate": {
    "direction": "long",
    "setup_type": "breakout_retest",
    "entry_zone": [68180, 68220],
    "planned_entry": 68180,
    "stop_loss": 67990,
    "take_profit": {
      "tp1": 123000,
      "tp2": 123000
    },
    "risk_reward": {
      "tp1": 2.0,
      "tp2": 3.0
    },
    "distance_to_support": 123,
    "distance_to_resistance": 123,
    "sl_distance": 123,
    "tp_distance": {
      "tp1": 123,
      "tp2": 123
    }
  },
  "timeframes": {
    "4h": {
      "current_price": 68290,
      "support": 123000,
      "resistance": 123000,
      "rsi14": 123000,
      "atr14": 123000,
      "ema20": 123000,
      "ema50": 123000,
      "ema100": 123000,
      "ema200": 123000,
      "distance_to_support": 123,
      "distance_to_resistance": 123,
      "trend_state": "bullish",
      "ema_alignment": "bullish",
      "structure_state": "HH_HL",
      "candles": [
        {
          "open_time": "1499040000000",
          "open": 1230000,
          "high": 123000,
          "low": 123000,
          "close": 123000,
          "volume": 123000,
          "close_time": "1499040000000",
          "quote_asset_volume": 2434.19055334,
          "number_of_trades": 308
        },
        {
          "open_time": "1499040000000",
          "open": 1230000,
          "high": 123000,
          "low": 123000,
          "close": 123000,
          "volume": 123000,
          "close_time": "1499040000000",
          "quote_asset_volume": 2434.19055334,
          "number_of_trades": 308
        },
        {
          "open_time": "1499040000000",
          "open": 1230000,
          "high": 123000,
          "low": 123000,
          "close": 123000,
          "volume": 123000,
          "close_time": "1499040000000",
          "quote_asset_volume": 2434.19055334,
          "number_of_trades": 308
        },
        {
          "open_time": "1499040000000",
          "open": 1230000,
          "high": 123000,
          "low": 123000,
          "close": 123000,
          "volume": 123000,
          "close_time": "1499040000000",
          "quote_asset_volume": 2434.19055334,
          "number_of_trades": 308
        },
        {
          "open_time": "1499040000000",
          "open": 1230000,
          "high": 123000,
          "low": 123000,
          "close": 123000,
          "volume": 123000,
          "close_time": "1499040000000",
          "quote_asset_volume": 2434.19055334,
          "number_of_trades": 308
        },
        {
          "open_time": "1499040000000",
          "open": 1230000,
          "high": 123000,
          "low": 123000,
          "close": 123000,
          "volume": 123000,
          "close_time": "1499040000000",
          "quote_asset_volume": 2434.19055334,
          "number_of_trades": 308
        },
        {
          "open_time": "1499040000000",
          "open": 1230000,
          "high": 123000,
          "low": 123000,
          "close": 123000,
          "volume": 123000,
          "close_time": "1499040000000",
          "quote_asset_volume": 2434.19055334,
          "number_of_trades": 308
        },
        {
          "open_time": "1499040000000",
          "open": 1230000,
          "high": 123000,
          "low": 123000,
          "close": 123000,
          "volume": 123000,
          "close_time": "1499040000000",
          "quote_asset_volume": 2434.19055334,
          "number_of_trades": 308
        },
        {
          "open_time": "1499040000000",
          "open": 1230000,
          "high": 123000,
          "low": 123000,
          "close": 123000,
          "volume": 123000,
          "close_time": "1499040000000",
          "quote_asset_volume": 2434.19055334,
          "number_of_trades": 308
        },
        {
          "open_time": "1499040000000",
          "open": 1230000,
          "high": 123000,
          "low": 123000,
          "close": 123000,
          "volume": 123000,
          "close_time": "1499040000000",
          "quote_asset_volume": 2434.19055334,
          "number_of_trades": 308
        },
        {
          "open_time": "1499040000000",
          "open": 1230000,
          "high": 123000,
          "low": 123000,
          "close": 123000,
          "volume": 123000,
          "close_time": "1499040000000",
          "quote_asset_volume": 2434.19055334,
          "number_of_trades": 308
        },
        {
          "open_time": "1499040000000",
          "open": 1230000,
          "high": 123000,
          "low": 123000,
          "close": 123000,
          "volume": 123000,
          "close_time": "1499040000000",
          "quote_asset_volume": 2434.19055334,
          "number_of_trades": 308
        },
        {
          "open_time": "1499040000000",
          "open": 1230000,
          "high": 123000,
          "low": 123000,
          "close": 123000,
          "volume": 123000,
          "close_time": "1499040000000",
          "quote_asset_volume": 2434.19055334,
          "number_of_trades": 308
        },
        {
          "open_time": "1499040000000",
          "open": 1230000,
          "high": 123000,
          "low": 123000,
          "close": 123000,
          "volume": 123000,
          "close_time": "1499040000000",
          "quote_asset_volume": 2434.19055334,
          "number_of_trades": 308
        },
        {
          "open_time": "1499040000000",
          "open": 1230000,
          "high": 123000,
          "low": 123000,
          "close": 123000,
          "volume": 123000,
          "close_time": "1499040000000",
          "quote_asset_volume": 2434.19055334,
          "number_of_trades": 308
        },
        {
          "open_time": "1499040000000",
          "open": 1230000,
          "high": 123000,
          "low": 123000,
          "close": 123000,
          "volume": 123000,
          "close_time": "1499040000000",
          "quote_asset_volume": 2434.19055334,
          "number_of_trades": 308
        },
        {
          "open_time": "1499040000000",
          "open": 1230000,
          "high": 123000,
          "low": 123000,
          "close": 123000,
          "volume": 123000,
          "close_time": "1499040000000",
          "quote_asset_volume": 2434.19055334,
          "number_of_trades": 308
        },
        {
          "open_time": "1499040000000",
          "open": 1230000,
          "high": 123000,
          "low": 123000,
          "close": 123000,
          "volume": 123000,
          "close_time": "1499040000000",
          "quote_asset_volume": 2434.19055334,
          "number_of_trades": 308
        },
        {
          "open_time": "1499040000000",
          "open": 1230000,
          "high": 123000,
          "low": 123000,
          "close": 123000,
          "volume": 123000,
          "close_time": "1499040000000",
          "quote_asset_volume": 2434.19055334,
          "number_of_trades": 308
        },
        {
          "open_time": "1499040000000",
          "open": 1230000,
          "high": 123000,
          "low": 123000,
          "close": 123000,
          "volume": 123000,
          "close_time": "1499040000000",
          "quote_asset_volume": 2434.19055334,
          "number_of_trades": 308
        },
        {
          "open_time": "1499040000000",
          "open": 1230000,
          "high": 123000,
          "low": 123000,
          "close": 123000,
          "volume": 123000,
          "close_time": "1499040000000",
          "quote_asset_volume": 2434.19055334,
          "number_of_trades": 308
        },
        {
          "open_time": "1499040000000",
          "open": 1230000,
          "high": 123000,
          "low": 123000,
          "close": 123000,
          "volume": 123000,
          "close_time": "1499040000000",
          "quote_asset_volume": 2434.19055334,
          "number_of_trades": 308
        }
      ]
    },
    "1h": {
      "current_price": 123,
      "support": 123000,
      "resistance": 123000,
      "rsi14": 123000,
      "atr14": 123000,
      "ema20": 123000,
      "ema50": 123000,
      "ema100": 123000,
      "ema200": 123000,
      "distance_to_support": 123,
      "distance_to_resistance": 123,
      "trend_state": "bullish",
      "ema_alignment": "bullish",
      "structure_state": "HH_HL",
      "candles": [
        {
          "open_time": "1499040000000",
          "open": 1230000,
          "high": 123000,
          "low": 123000,
          "close": 123000,
          "volume": 123000,
          "close_time": "1499040000000",
          "quote_asset_volume": 2434.19055334,
          "number_of_trades": 308
        },
        {
          "open_time": "1499040000000",
          "open": 1230000,
          "high": 123000,
          "low": 123000,
          "close": 123000,
          "volume": 123000,
          "close_time": "1499040000000",
          "quote_asset_volume": 2434.19055334,
          "number_of_trades": 308
        },
        {
          "open_time": "1499040000000",
          "open": 1230000,
          "high": 123000,
          "low": 123000,
          "close": 123000,
          "volume": 123000,
          "close_time": "1499040000000",
          "quote_asset_volume": 2434.19055334,
          "number_of_trades": 308
        },
        {
          "open_time": "1499040000000",
          "open": 1230000,
          "high": 123000,
          "low": 123000,
          "close": 123000,
          "volume": 123000,
          "close_time": "1499040000000",
          "quote_asset_volume": 2434.19055334,
          "number_of_trades": 308
        },
        {
          "open_time": "1499040000000",
          "open": 1230000,
          "high": 123000,
          "low": 123000,
          "close": 123000,
          "volume": 123000,
          "close_time": "1499040000000",
          "quote_asset_volume": 2434.19055334,
          "number_of_trades": 308
        },
        {
          "open_time": "1499040000000",
          "open": 1230000,
          "high": 123000,
          "low": 123000,
          "close": 123000,
          "volume": 123000,
          "close_time": "1499040000000",
          "quote_asset_volume": 2434.19055334,
          "number_of_trades": 308
        },
        {
          "open_time": "1499040000000",
          "open": 1230000,
          "high": 123000,
          "low": 123000,
          "close": 123000,
          "volume": 123000,
          "close_time": "1499040000000",
          "quote_asset_volume": 2434.19055334,
          "number_of_trades": 308
        },
        {
          "open_time": "1499040000000",
          "open": 1230000,
          "high": 123000,
          "low": 123000,
          "close": 123000,
          "volume": 123000,
          "close_time": "1499040000000",
          "quote_asset_volume": 2434.19055334,
          "number_of_trades": 308
        },
        {
          "open_time": "1499040000000",
          "open": 1230000,
          "high": 123000,
          "low": 123000,
          "close": 123000,
          "volume": 123000,
          "close_time": "1499040000000",
          "quote_asset_volume": 2434.19055334,
          "number_of_trades": 308
        },
        {
          "open_time": "1499040000000",
          "open": 1230000,
          "high": 123000,
          "low": 123000,
          "close": 123000,
          "volume": 123000,
          "close_time": "1499040000000",
          "quote_asset_volume": 2434.19055334,
          "number_of_trades": 308
        },
        {
          "open_time": "1499040000000",
          "open": 1230000,
          "high": 123000,
          "low": 123000,
          "close": 123000,
          "volume": 123000,
          "close_time": "1499040000000",
          "quote_asset_volume": 2434.19055334,
          "number_of_trades": 308
        },
        {
          "open_time": "1499040000000",
          "open": 1230000,
          "high": 123000,
          "low": 123000,
          "close": 123000,
          "volume": 123000,
          "close_time": "1499040000000",
          "quote_asset_volume": 2434.19055334,
          "number_of_trades": 308
        },
        {
          "open_time": "1499040000000",
          "open": 1230000,
          "high": 123000,
          "low": 123000,
          "close": 123000,
          "volume": 123000,
          "close_time": "1499040000000",
          "quote_asset_volume": 2434.19055334,
          "number_of_trades": 308
        },
        {
          "open_time": "1499040000000",
          "open": 1230000,
          "high": 123000,
          "low": 123000,
          "close": 123000,
          "volume": 123000,
          "close_time": "1499040000000",
          "quote_asset_volume": 2434.19055334,
          "number_of_trades": 308
        },
        {
          "open_time": "1499040000000",
          "open": 1230000,
          "high": 123000,
          "low": 123000,
          "close": 123000,
          "volume": 123000,
          "close_time": "1499040000000",
          "quote_asset_volume": 2434.19055334,
          "number_of_trades": 308
        },
        {
          "open_time": "1499040000000",
          "open": 1230000,
          "high": 123000,
          "low": 123000,
          "close": 123000,
          "volume": 123000,
          "close_time": "1499040000000",
          "quote_asset_volume": 2434.19055334,
          "number_of_trades": 308
        },
        {
          "open_time": "1499040000000",
          "open": 1230000,
          "high": 123000,
          "low": 123000,
          "close": 123000,
          "volume": 123000,
          "close_time": "1499040000000",
          "quote_asset_volume": 2434.19055334,
          "number_of_trades": 308
        },
        {
          "open_time": "1499040000000",
          "open": 1230000,
          "high": 123000,
          "low": 123000,
          "close": 123000,
          "volume": 123000,
          "close_time": "1499040000000",
          "quote_asset_volume": 2434.19055334,
          "number_of_trades": 308
        },
        {
          "open_time": "1499040000000",
          "open": 1230000,
          "high": 123000,
          "low": 123000,
          "close": 123000,
          "volume": 123000,
          "close_time": "1499040000000",
          "quote_asset_volume": 2434.19055334,
          "number_of_trades": 308
        },
        {
          "open_time": "1499040000000",
          "open": 1230000,
          "high": 123000,
          "low": 123000,
          "close": 123000,
          "volume": 123000,
          "close_time": "1499040000000",
          "quote_asset_volume": 2434.19055334,
          "number_of_trades": 308
        },
        {
          "open_time": "1499040000000",
          "open": 1230000,
          "high": 123000,
          "low": 123000,
          "close": 123000,
          "volume": 123000,
          "close_time": "1499040000000",
          "quote_asset_volume": 2434.19055334,
          "number_of_trades": 308
        },
        {
          "open_time": "1499040000000",
          "open": 1230000,
          "high": 123000,
          "low": 123000,
          "close": 123000,
          "volume": 123000,
          "close_time": "1499040000000",
          "quote_asset_volume": 2434.19055334,
          "number_of_trades": 308
        }
      ]
    },
    "15m": {
      "current_price": 123,
      "support": 123000,
      "resistance": 123000,
      "rsi14": 123000,
      "atr14": 123000,
      "ema20": 123000,
      "ema50": 123000,
      "ema100": 123000,
      "ema200": 123000,
      "distance_to_support": 123,
      "distance_to_resistance": 123,
      "trend_state": "bullish",
      "ema_alignment": "bullish",
      "structure_state": "HH_HL",
      "candles": [
        {
          "open_time": "1499040000000",
          "open": 1230000,
          "high": 123000,
          "low": 123000,
          "close": 123000,
          "volume": 123000,
          "close_time": "1499040000000",
          "quote_asset_volume": 2434.19055334,
          "number_of_trades": 308
        },
        {
          "open_time": "1499040000000",
          "open": 1230000,
          "high": 123000,
          "low": 123000,
          "close": 123000,
          "volume": 123000,
          "close_time": "1499040000000",
          "quote_asset_volume": 2434.19055334,
          "number_of_trades": 308
        },
        {
          "open_time": "1499040000000",
          "open": 1230000,
          "high": 123000,
          "low": 123000,
          "close": 123000,
          "volume": 123000,
          "close_time": "1499040000000",
          "quote_asset_volume": 2434.19055334,
          "number_of_trades": 308
        },
        {
          "open_time": "1499040000000",
          "open": 1230000,
          "high": 123000,
          "low": 123000,
          "close": 123000,
          "volume": 123000,
          "close_time": "1499040000000",
          "quote_asset_volume": 2434.19055334,
          "number_of_trades": 308
        },
        {
          "open_time": "1499040000000",
          "open": 1230000,
          "high": 123000,
          "low": 123000,
          "close": 123000,
          "volume": 123000,
          "close_time": "1499040000000",
          "quote_asset_volume": 2434.19055334,
          "number_of_trades": 308
        },
        {
          "open_time": "1499040000000",
          "open": 1230000,
          "high": 123000,
          "low": 123000,
          "close": 123000,
          "volume": 123000,
          "close_time": "1499040000000",
          "quote_asset_volume": 2434.19055334,
          "number_of_trades": 308
        },
        {
          "open_time": "1499040000000",
          "open": 1230000,
          "high": 123000,
          "low": 123000,
          "close": 123000,
          "volume": 123000,
          "close_time": "1499040000000",
          "quote_asset_volume": 2434.19055334,
          "number_of_trades": 308
        },
        {
          "open_time": "1499040000000",
          "open": 1230000,
          "high": 123000,
          "low": 123000,
          "close": 123000,
          "volume": 123000,
          "close_time": "1499040000000",
          "quote_asset_volume": 2434.19055334,
          "number_of_trades": 308
        },
        {
          "open_time": "1499040000000",
          "open": 1230000,
          "high": 123000,
          "low": 123000,
          "close": 123000,
          "volume": 123000,
          "close_time": "1499040000000",
          "quote_asset_volume": 2434.19055334,
          "number_of_trades": 308
        },
        {
          "open_time": "1499040000000",
          "open": 1230000,
          "high": 123000,
          "low": 123000,
          "close": 123000,
          "volume": 123000,
          "close_time": "1499040000000",
          "quote_asset_volume": 2434.19055334,
          "number_of_trades": 308
        },
        {
          "open_time": "1499040000000",
          "open": 1230000,
          "high": 123000,
          "low": 123000,
          "close": 123000,
          "volume": 123000,
          "close_time": "1499040000000",
          "quote_asset_volume": 2434.19055334,
          "number_of_trades": 308
        },
        {
          "open_time": "1499040000000",
          "open": 1230000,
          "high": 123000,
          "low": 123000,
          "close": 123000,
          "volume": 123000,
          "close_time": "1499040000000",
          "quote_asset_volume": 2434.19055334,
          "number_of_trades": 308
        },
        {
          "open_time": "1499040000000",
          "open": 1230000,
          "high": 123000,
          "low": 123000,
          "close": 123000,
          "volume": 123000,
          "close_time": "1499040000000",
          "quote_asset_volume": 2434.19055334,
          "number_of_trades": 308
        },
        {
          "open_time": "1499040000000",
          "open": 1230000,
          "high": 123000,
          "low": 123000,
          "close": 123000,
          "volume": 123000,
          "close_time": "1499040000000",
          "quote_asset_volume": 2434.19055334,
          "number_of_trades": 308
        },
        {
          "open_time": "1499040000000",
          "open": 1230000,
          "high": 123000,
          "low": 123000,
          "close": 123000,
          "volume": 123000,
          "close_time": "1499040000000",
          "quote_asset_volume": 2434.19055334,
          "number_of_trades": 308
        },
        {
          "open_time": "1499040000000",
          "open": 1230000,
          "high": 123000,
          "low": 123000,
          "close": 123000,
          "volume": 123000,
          "close_time": "1499040000000",
          "quote_asset_volume": 2434.19055334,
          "number_of_trades": 308
        },
        {
          "open_time": "1499040000000",
          "open": 1230000,
          "high": 123000,
          "low": 123000,
          "close": 123000,
          "volume": 123000,
          "close_time": "1499040000000",
          "quote_asset_volume": 2434.19055334,
          "number_of_trades": 308
        },
        {
          "open_time": "1499040000000",
          "open": 1230000,
          "high": 123000,
          "low": 123000,
          "close": 123000,
          "volume": 123000,
          "close_time": "1499040000000",
          "quote_asset_volume": 2434.19055334,
          "number_of_trades": 308
        },
        {
          "open_time": "1499040000000",
          "open": 1230000,
          "high": 123000,
          "low": 123000,
          "close": 123000,
          "volume": 123000,
          "close_time": "1499040000000",
          "quote_asset_volume": 2434.19055334,
          "number_of_trades": 308
        },
        {
          "open_time": "1499040000000",
          "open": 1230000,
          "high": 123000,
          "low": 123000,
          "close": 123000,
          "volume": 123000,
          "close_time": "1499040000000",
          "quote_asset_volume": 2434.19055334,
          "number_of_trades": 308
        },
        {
          "open_time": "1499040000000",
          "open": 1230000,
          "high": 123000,
          "low": 123000,
          "close": 123000,
          "volume": 123000,
          "close_time": "1499040000000",
          "quote_asset_volume": 2434.19055334,
          "number_of_trades": 308
        },
        {
          "open_time": "1499040000000",
          "open": 1230000,
          "high": 123000,
          "low": 123000,
          "close": 123000,
          "volume": 123000,
          "close_time": "1499040000000",
          "quote_asset_volume": 2434.19055334,
          "number_of_trades": 308
        }
      ]
    },
    "1m": {
      "current_price": 123,
      "support": 123000,
      "resistance": 123000,
      "rsi14": 123000,
      "atr14": 123000,
      "ema20": 123000,
      "ema50": 123000,
      "ema100": 123000,
      "ema200": 123000,
      "distance_to_support": 123,
      "distance_to_resistance": 123,
      "trend_state": "bullish",
      "ema_alignment": "bullish",
      "structure_state": "HH_HL",
      "candles": [
        {
          "open_time": "1499040000000",
          "open": 1230000,
          "high": 123000,
          "low": 123000,
          "close": 123000,
          "volume": 123000,
          "close_time": "1499040000000",
          "quote_asset_volume": 2434.19055334,
          "number_of_trades": 308
        },
        {
          "open_time": "1499040000000",
          "open": 1230000,
          "high": 123000,
          "low": 123000,
          "close": 123000,
          "volume": 123000,
          "close_time": "1499040000000",
          "quote_asset_volume": 2434.19055334,
          "number_of_trades": 308
        },
        {
          "open_time": "1499040000000",
          "open": 1230000,
          "high": 123000,
          "low": 123000,
          "close": 123000,
          "volume": 123000,
          "close_time": "1499040000000",
          "quote_asset_volume": 2434.19055334,
          "number_of_trades": 308
        },
        {
          "open_time": "1499040000000",
          "open": 1230000,
          "high": 123000,
          "low": 123000,
          "close": 123000,
          "volume": 123000,
          "close_time": "1499040000000",
          "quote_asset_volume": 2434.19055334,
          "number_of_trades": 308
        },
        {
          "open_time": "1499040000000",
          "open": 1230000,
          "high": 123000,
          "low": 123000,
          "close": 123000,
          "volume": 123000,
          "close_time": "1499040000000",
          "quote_asset_volume": 2434.19055334,
          "number_of_trades": 308
        },
        {
          "open_time": "1499040000000",
          "open": 1230000,
          "high": 123000,
          "low": 123000,
          "close": 123000,
          "volume": 123000,
          "close_time": "1499040000000",
          "quote_asset_volume": 2434.19055334,
          "number_of_trades": 308
        },
        {
          "open_time": "1499040000000",
          "open": 1230000,
          "high": 123000,
          "low": 123000,
          "close": 123000,
          "volume": 123000,
          "close_time": "1499040000000",
          "quote_asset_volume": 2434.19055334,
          "number_of_trades": 308
        },
        {
          "open_time": "1499040000000",
          "open": 1230000,
          "high": 123000,
          "low": 123000,
          "close": 123000,
          "volume": 123000,
          "close_time": "1499040000000",
          "quote_asset_volume": 2434.19055334,
          "number_of_trades": 308
        },
        {
          "open_time": "1499040000000",
          "open": 1230000,
          "high": 123000,
          "low": 123000,
          "close": 123000,
          "volume": 123000,
          "close_time": "1499040000000",
          "quote_asset_volume": 2434.19055334,
          "number_of_trades": 308
        },
        {
          "open_time": "1499040000000",
          "open": 1230000,
          "high": 123000,
          "low": 123000,
          "close": 123000,
          "volume": 123000,
          "close_time": "1499040000000",
          "quote_asset_volume": 2434.19055334,
          "number_of_trades": 308
        },
        {
          "open_time": "1499040000000",
          "open": 1230000,
          "high": 123000,
          "low": 123000,
          "close": 123000,
          "volume": 123000,
          "close_time": "1499040000000",
          "quote_asset_volume": 2434.19055334,
          "number_of_trades": 308
        },
        {
          "open_time": "1499040000000",
          "open": 1230000,
          "high": 123000,
          "low": 123000,
          "close": 123000,
          "volume": 123000,
          "close_time": "1499040000000",
          "quote_asset_volume": 2434.19055334,
          "number_of_trades": 308
        },
        {
          "open_time": "1499040000000",
          "open": 1230000,
          "high": 123000,
          "low": 123000,
          "close": 123000,
          "volume": 123000,
          "close_time": "1499040000000",
          "quote_asset_volume": 2434.19055334,
          "number_of_trades": 308
        },
        {
          "open_time": "1499040000000",
          "open": 1230000,
          "high": 123000,
          "low": 123000,
          "close": 123000,
          "volume": 123000,
          "close_time": "1499040000000",
          "quote_asset_volume": 2434.19055334,
          "number_of_trades": 308
        },
        {
          "open_time": "1499040000000",
          "open": 1230000,
          "high": 123000,
          "low": 123000,
          "close": 123000,
          "volume": 123000,
          "close_time": "1499040000000",
          "quote_asset_volume": 2434.19055334,
          "number_of_trades": 308
        },
        {
          "open_time": "1499040000000",
          "open": 1230000,
          "high": 123000,
          "low": 123000,
          "close": 123000,
          "volume": 123000,
          "close_time": "1499040000000",
          "quote_asset_volume": 2434.19055334,
          "number_of_trades": 308
        },
        {
          "open_time": "1499040000000",
          "open": 1230000,
          "high": 123000,
          "low": 123000,
          "close": 123000,
          "volume": 123000,
          "close_time": "1499040000000",
          "quote_asset_volume": 2434.19055334,
          "number_of_trades": 308
        },
        {
          "open_time": "1499040000000",
          "open": 1230000,
          "high": 123000,
          "low": 123000,
          "close": 123000,
          "volume": 123000,
          "close_time": "1499040000000",
          "quote_asset_volume": 2434.19055334,
          "number_of_trades": 308
        },
        {
          "open_time": "1499040000000",
          "open": 1230000,
          "high": 123000,
          "low": 123000,
          "close": 123000,
          "volume": 123000,
          "close_time": "1499040000000",
          "quote_asset_volume": 2434.19055334,
          "number_of_trades": 308
        },
        {
          "open_time": "1499040000000",
          "open": 1230000,
          "high": 123000,
          "low": 123000,
          "close": 123000,
          "volume": 123000,
          "close_time": "1499040000000",
          "quote_asset_volume": 2434.19055334,
          "number_of_trades": 308
        },
        {
          "open_time": "1499040000000",
          "open": 1230000,
          "high": 123000,
          "low": 123000,
          "close": 123000,
          "volume": 123000,
          "close_time": "1499040000000",
          "quote_asset_volume": 2434.19055334,
          "number_of_trades": 308
        },
        {
          "open_time": "1499040000000",
          "open": 1230000,
          "high": 123000,
          "low": 123000,
          "close": 123000,
          "volume": 123000,
          "close_time": "1499040000000",
          "quote_asset_volume": 2434.19055334,
          "number_of_trades": 308
        }
      ]
    }
  }
}
